mvupkg_rstanic/__init__.py
mvupkg_rstanic/mvupkg_rstanic.ctf
mvupkg_rstanic/algorithms/__init__.py
mvupkg_rstanic/algorithms/mvu.py
mvupkg_rstanic-2.4.dist-info/METADATA
mvupkg_rstanic-2.4.dist-info/WHEEL
mvupkg_rstanic-2.4.dist-info/top_level.txt
mvupkg_rstanic-2.4.dist-info/RECORD
