Metadata-Version: 2.1
Name: mvupkg-rstanic
Version: 2.4
Summary: A Python interface to MATLAB implementation of MVU algorithm.
Platform: Linux
Platform: Windows
Platform: macOS
